README.md
setup.cfg
setup.py
G4EPP/G4EPP.py
G4EPP/__init__.py
G4EPP.egg-info/PKG-INFO
G4EPP.egg-info/SOURCES.txt
G4EPP.egg-info/dependency_links.txt
G4EPP.egg-info/requires.txt
G4EPP.egg-info/top_level.txt