Metadata-Version: 1.1
Name: G4EPP
Version: 0.0.6
Summary: GEANT4 EPP Simulation wrapper
Home-page: UNKNOWN
Author: Grant Berland
Author-email: grant.berland@colorado.edu
License: UNKNOWN
Keywords: python,EPP
Platform: UNKNOWN
Classifier: Development Status :: 3 - Alpha
Classifier: License :: OSI Approved :: MIT License
Classifier: Programming Language :: Python :: 3.6
